antix/__init__.py
antyx/__init__.py
antyx/principals/__init__.py
antyx/principals/data_loader.py
antyx/principals/report.py
antyx/styles/__init__.py
antyx/utils/__init__.py
antyx/utils/correlations.py
antyx/utils/lines.py
antyx/utils/outliers.py
antyx/utils/profiles.py
antyx/utils/summary.py
antyx/utils/types.py
antyx/utils/utils.py
antyx/utils/visualizations.py
antyx-0.1.6.dist-info/METADATA
antyx-0.1.6.dist-info/WHEEL
antyx-0.1.6.dist-info/top_level.txt
antyx-0.1.6.dist-info/RECORD
